sbapi/__init__.py
sbapi-0.0.5.dist-info/METADATA
sbapi-0.0.5.dist-info/WHEEL
sbapi-0.0.5.dist-info/top_level.txt
sbapi-0.0.5.dist-info/RECORD
