Metadata-Version: 2.1
Name: sbapi
Version: 0.0.5
Summary: API Wrapper for Hypixel Skyblock.
Author: carreb, drawbridge
Author-email: <gabemackta@gmail.com>
License: UNKNOWN
Keywords: python,requests,api,hypixel,skyblock
Platform: UNKNOWN
Classifier: Development Status :: 1 - Planning
Classifier: Intended Audience :: Developers
Classifier: Programming Language :: Python :: 3
Classifier: Operating System :: Unix
Classifier: Operating System :: MacOS :: MacOS X
Classifier: Operating System :: Microsoft :: Windows
Requires-Dist: requests
